{"archive_len": 4, "initial population time": "0:00:00.005999", "evaluation process time": "0:18:26.292951", "distance calculation time": "0:01:36.485529", "whole generation time": "0:20:02.784479", "operation_type": "changing the fog density", "fog_average_amount": 0.1174136793218313, "rain_average_amount": 0.0, "foam_average_amount": 0.0, "ripple_average_amount": 0.0, "bump_average_amount": 0.0, "position_obstacle_average_amount": 0.0, "illumintaion_average_amount": 0.0, "normalize_distance_fog": 0.1174136793218313, "normalize_distance_rain": 0.0, "normalize_distance_foam": 0.0, "normalize_distance_ripple": 0.0, "normalize_distance_bump": 0.0, "normalize_distance_obstacle": 0.0, "normalize_distance_illumination": 0.0, "normalize_distance_road_shape": 0.075, "radius": 0.075, "angle": 0.0, "diameter_out": 60.02193849416847, "diameter_in": 59.947264004619704}