{"archive_len": 9, "initial population time": "0:00:00.002995", "evaluation process time": "0:11:23.889563", "distance calculation time": "0:01:29.102541", "whole generation time": "0:12:52.995099", "operation_type": "changing the fog density", "fog_average_amount": 0.13046485103371364, "rain_average_amount": 0.0, "foam_average_amount": 0.0, "ripple_average_amount": 0.0, "bump_average_amount": 0.0, "position_obstacle_average_amount": 0.0, "illumintaion_average_amount": 0.0, "normalize_distance_fog": 0.13046485103371364, "normalize_distance_rain": 0.0, "normalize_distance_foam": 0.0, "normalize_distance_ripple": 0.0, "normalize_distance_bump": 0.0, "normalize_distance_obstacle": 0.0, "normalize_distance_illumination": 0.0, "normalize_distance_road_shape": 0.06833333333333333, "radius": 0.06833333333333333, "angle": 0.0, "diameter_out": 58.356896371946696, "diameter_in": 58.31970368304542}