{"archive_len": 12, "initial population time": "0:00:00.011998", "evaluation process time": "0:33:24.647676", "distance calculation time": "0:06:18.352058", "whole generation time": "0:39:43.011732", "operation_type": "changing the fog density", "fog_average_amount": 0.19369390469614675, "rain_average_amount": 0.0, "foam_average_amount": 0.0, "ripple_average_amount": 0.0, "bump_average_amount": 0.0, "position_obstacle_average_amount": 0.0, "illumintaion_average_amount": 0.0, "normalize_distance_fog": 0.19369390469614675, "normalize_distance_rain": 0.0, "normalize_distance_foam": 0.0, "normalize_distance_ripple": 0.0, "normalize_distance_bump": 0.0, "normalize_distance_obstacle": 0.0, "normalize_distance_illumination": 0.0, "normalize_distance_road_shape": 0.1375, "radius": 0.1375, "angle": 0.0, "diameter_out": 58.59741394841482, "diameter_in": 58.57149632739219}